matiq.py
matiq-0.0.1.dist-info/LICENSE
matiq-0.0.1.dist-info/METADATA
matiq-0.0.1.dist-info/WHEEL
matiq-0.0.1.dist-info/top_level.txt
matiq-0.0.1.dist-info/RECORD
