Metadata-Version: 2.1
Name: matiq
Version: 0.0.1
Summary: Package for Matiq Tests
Home-page: UNKNOWN
License: UNKNOWN
Platform: UNKNOWN
License-File: LICENSE
